capitalist/__init__.py
capitalist/auth.py
capitalist/capitalist.py
capitalist/const.py
capitalist/exceptions.py
capitalist/models.py
capitalist/request_executor.py
capitalist/utils.py
capitalist/contrib/__init__.py
capitalist/contrib/django/__init__.py
capitalist/contrib/django/django_capitalist/__init__.py
capitalist/contrib/django/django_capitalist/admin.py
capitalist/contrib/django/django_capitalist/apps.py
capitalist/contrib/django/django_capitalist/models.py
capitalist/contrib/django/django_capitalist/validators.py
capitalist/contrib/django/django_capitalist/locale/ru/LC_MESSAGES/django.mo
capitalist/contrib/django/django_capitalist/locale/ru/LC_MESSAGES/django.po
capitalist/contrib/django/django_capitalist/management/__init__.py
capitalist/contrib/django/django_capitalist/management/commands/__init__.py
capitalist/contrib/django/django_capitalist/management/commands/load_accounts.py
capitalist/contrib/django/django_capitalist/migrations/0001_initial.py
capitalist/contrib/django/django_capitalist/migrations/0002_auto_20190328_1508.py
capitalist/contrib/django/django_capitalist/migrations/__init__.py
python_capitalist-1.3.1.dist-info/LICENSE.md
python_capitalist-1.3.1.dist-info/METADATA
python_capitalist-1.3.1.dist-info/WHEEL
python_capitalist-1.3.1.dist-info/top_level.txt
python_capitalist-1.3.1.dist-info/RECORD
