Metadata-Version: 2.1
Name: python-capitalist
Version: 1.3.1
Summary: Python/Django client for capitalist.net
Home-page: https://github.com/mpyrev/python-capitalist
Author: Mikhail Pyrev
Author-email: mikhail.pyrev@gmail.com
License: UNKNOWN
Project-URL: Bug Reports, https://github.com/mpyrev/python-capitalist/issues
Project-URL: Source, https://github.com/mpyrev/python-capitalist
Keywords: development django capitalist
Platform: UNKNOWN
Classifier: Development Status :: 5 - Production/Stable
Classifier: Intended Audience :: Developers
Classifier: License :: OSI Approved :: MIT License
Classifier: Programming Language :: Python :: 3
Classifier: Programming Language :: Python :: 3.5
Classifier: Programming Language :: Python :: 3.6
Classifier: Programming Language :: Python :: 3.7
Classifier: Programming Language :: Python :: 3.8
Requires-Python: >=3.5
License-File: LICENSE.md
Requires-Dist: requests
Requires-Dist: cryptography
Provides-Extra: django
Requires-Dist: Django ; extra == 'django'
